audiodb/__init__.py
audiodb/audiodb.py
audiodb-1.0.0.dist-info/LICENSE
audiodb-1.0.0.dist-info/METADATA
audiodb-1.0.0.dist-info/WHEEL
audiodb-1.0.0.dist-info/top_level.txt
audiodb-1.0.0.dist-info/RECORD
