Metadata-Version: 2.1
Name: audiodb
Version: 1.0.0
Summary: TheAudioDB API client
Home-page: https://github.com/thexxiv/audiodb-py
Author: XXIV
License: UNKNOWN
Project-URL: Bug Tracker, https://github.com/thexxiv/audiodb-py/issues
Platform: UNKNOWN
Classifier: Programming Language :: Python :: 3
Classifier: License :: OSI Approved :: Apache Software License
Classifier: Operating System :: OS Independent
Requires-Python: >=3.6
License-File: LICENSE
